cryolite/__init__.py
cryolite-0.0.0.dist-info/METADATA
cryolite-0.0.0.dist-info/WHEEL
cryolite-0.0.0.dist-info/top_level.txt
cryolite-0.0.0.dist-info/RECORD
