Metadata-Version: 2.4
Name: cryolite
Version: 0.0.0
Summary: CRYOLITE runs your Open Lightweight Iceberg Table Engine.
Author: cryolite.io
Project-URL: Homepage, https://cryolite.io
Project-URL: Repository, https://github.com/cryolite-io/cryolite-python
Project-URL: Issues, https://github.com/cryolite-io/cryolite-python/issues
Keywords: iceberg,arrow,calcite,lakehouse,query-engine
Requires-Python: >=3.9
